quarkle_monitoring/__init__.py
quarkle_monitoring/auto_wrap.py
quarkle_monitoring/cache.py
quarkle_monitoring/errors.py
quarkle_monitoring/notifications.py
quarkle_monitoring/orchestrator.py
quarkle_monitoring/web_utils.py
quarkle_monitoring-0.1.11.dist-info/METADATA
quarkle_monitoring-0.1.11.dist-info/WHEEL
quarkle_monitoring-0.1.11.dist-info/RECORD
